LICENSE
MANIFEST.in
README.md
requirements.txt
setup.cfg
setup.py
bravaweb/__init__.py
bravaweb/application.py
bravaweb/controller.py
bravaweb/enviroment.py
bravaweb.egg-info/PKG-INFO
bravaweb.egg-info/SOURCES.txt
bravaweb.egg-info/dependency_links.txt
bravaweb.egg-info/requires.txt
bravaweb.egg-info/top_level.txt
bravaweb/response/__init__.py
bravaweb/response/css.py
bravaweb/response/csv.py
bravaweb/response/html.py
bravaweb/response/javascript.py
bravaweb/response/jpg.py
bravaweb/response/json.py
bravaweb/response/mp4.py
bravaweb/response/pdf.py
bravaweb/response/png.py
bravaweb/response/textplain.py
bravaweb/response/webm.py
bravaweb/response/xml.py
bravaweb/response/lib/__init__.py
bravaweb/response/lib/object.py
bravaweb/response/lib/view.py
bravaweb/security/__init__.py
bravaweb/security/decorator.py
bravaweb/security/methods.py
bravaweb/security/origin.py
bravaweb/security/request_params.py
bravaweb/utils/__init__.py
bravaweb/utils/encoder.py
bravaweb/utils/request_body.py
bravaweb/utils/request_header.py
bravaweb/utils/request_methods.py
bravaweb/utils/response_code.py
bravaweb/utils/response_type.py
bravaweb/utils/templates.py
bravaweb/utils/log/__init__.py