Metadata-Version: 2.1
Name: bravaweb
Version: 0.0.13
Summary: BravaWeb Framework for ASGI Server
Home-page: https://github.com/robertons/bravaweb
Author: Roberto Neves
Author-email: robertonsilva@gmail.com
License: MIT
Keywords: asgi,wsgi,python3,web,http,framework,mysql,mariadb
Platform: UNKNOWN
Classifier: Development Status :: 3 - Alpha
Classifier: Environment :: Web Environment
Classifier: Intended Audience :: Developers
Classifier: Natural Language :: English
Classifier: Natural Language :: Portuguese (Brazilian)
Classifier: License :: OSI Approved :: MIT License
Classifier: Programming Language :: Python :: 3.6
